{
  "schemaVersion": 1,
  "id": "nucleus",
  "version": "${version}",

  "name": "Nucleus",
  "description": "An extensible registration library.",
  "authors": [
    "NiChrosia"
  ],
  "contact": {
    "homepage": "https://github.com/NiChrosia/Nucleus",
    "sources": "https://github.com/NiChrosia/Nucleus"
  },
  "icon": "assets/nucleus/icon.png",
  "license": "MIT",
  "accessWidener": "nucleus.accesswidener",
  "environment": "*",
  "mixins": [
    "nucleus.mixins.json"
  ],
  "depends": {
    "fabricloader": ">=0.8.7",
    "fabric": ">=0.42.0",
    "fabric-language-kotlin": "*",
    "minecraft": ">=1.18"
  }
}